cartoview/__init__.py
cartoview/celery.py
cartoview/log_handler.py
cartoview/settings.py
cartoview/urls.py
cartoview/version.py
cartoview/views.py
cartoview/wsgi.py
cartoview/app_manager/__init__.py
cartoview/app_manager/admin.py
cartoview/app_manager/api.py
cartoview/app_manager/config.py
cartoview/app_manager/context_processors.py
cartoview/app_manager/decorators.py
cartoview/app_manager/forms.py
cartoview/app_manager/helpers.py
cartoview/app_manager/installer.py
cartoview/app_manager/models.py
cartoview/app_manager/req_installer.py
cartoview/app_manager/resources.py
cartoview/app_manager/rest.py
cartoview/app_manager/serializers.py
cartoview/app_manager/settings.py
cartoview/app_manager/tests.py
cartoview/app_manager/urls.py
cartoview/app_manager/utils.py
cartoview/app_manager/views.py
cartoview/app_manager/fixtures/app_stores.json
cartoview/app_manager/fixtures/app_stores_exchange.json
cartoview/app_manager/fixtures/app_stores_qgis.json
cartoview/app_manager/management/__init__.py
cartoview/app_manager/management/commands/__init__.py
cartoview/app_manager/management/commands/install_app.py
cartoview/app_manager/management/commands/load_current_apps.py
cartoview/app_manager/management/commands/update_current_apps.py
cartoview/app_manager/migrations/0001_initial.py
cartoview/app_manager/migrations/0002_auto_20171001_1057.py
cartoview/app_manager/migrations/0003_auto_20171002_0445.py
cartoview/app_manager/migrations/0004_auto_20171002_0446.py
cartoview/app_manager/migrations/0005_delete_apptag.py
cartoview/app_manager/migrations/0006_app_default_config.py
cartoview/app_manager/migrations/0007_auto_20180128_0116.py
cartoview/app_manager/migrations/0008_appinstance_logo.py
cartoview/app_manager/migrations/0009_auto_20180920_1659.py
cartoview/app_manager/migrations/__init__.py
cartoview/app_manager/static/app_manager/css/appinstance_list.css
cartoview/app_manager/static/app_manager/css/manager.css
cartoview/app_manager/static/app_manager/img/no-image.jpg
cartoview-1.8.4.dist-info/LICENSE
cartoview-1.8.4.dist-info/METADATA
cartoview-1.8.4.dist-info/WHEEL
cartoview-1.8.4.dist-info/top_level.txt
cartoview-1.8.4.dist-info/RECORD
