Metadata-Version: 2.1
Name: cartoview
Version: 1.8.4
Summary: Cartoview is a GIS web mapping application framework to     easily share and deploy apps based on Geonode
Home-page: https://github.com/cartologic/cartoview
Author: Cartologic
Author-email: info@cartologic.com
License: BSD
Keywords: cartoview,gis,geonode,django,web mapping,applications,apps,application management
Platform: UNKNOWN
Classifier: Development Status :: 4 - Beta
Classifier: Framework :: Django :: 1.8
Classifier: Topic :: Scientific/Engineering :: GIS
Requires-Dist: future
Requires-Dist: six (==1.10.0)
Requires-Dist: portalocker (==1.2.1)
Requires-Dist: geonode (<2.9,>2.7.5.dev20180125135927)
Requires-Dist: Faker (>=0.8.4)
Requires-Dist: cherrypy (==11.0.0)
Requires-Dist: cheroot (==5.8.3)
